patronx/__init__.py
patronx/__main__.py
patronx/aws_store.py
patronx/backup.py
patronx/cli.py
patronx/config.py
patronx/env.py
patronx/logger.py
patronx/schedule.py
patronx/service.py
patronx/tasks.py
patronx-2.4.2.dist-info/licenses/LICENSE
patronx-2.4.2.dist-info/METADATA
patronx-2.4.2.dist-info/WHEEL
patronx-2.4.2.dist-info/entry_points.txt
patronx-2.4.2.dist-info/top_level.txt
patronx-2.4.2.dist-info/RECORD
