Metadata-Version: 2.4
Name: patronx
Version: 2.4.2
Summary: Simple package for backups and recovery
Author: xdanielsb
License: BSD-3-Clause
Requires-Python: >=3.12
License-File: LICENSE
Requires-Dist: click>=8.0
Requires-Dist: psycopg2-binary>=2.9
Requires-Dist: tqdm
Requires-Dist: boto3>=1.34
Requires-Dist: remoulade[rabbitmq,redis]==3.3.1
Requires-Dist: croniter>=6.0
Requires-Dist: python-dotenv>=1.0
Requires-Dist: python-logstash>=0.4.8
Provides-Extra: test
Requires-Dist: pytest; extra == "test"
Requires-Dist: pytest-cov; extra == "test"
Requires-Dist: ruff; extra == "test"
Requires-Dist: isort; extra == "test"
Requires-Dist: mypy; extra == "test"
Dynamic: license-file
